pyds-stubs/__init__.pyi
pyds-stubs/stub.pyi
pyds-stubs/typing.pyi
pyds_stubs-1.2.0.dist-info/licenses/LICENSE
pyds_stubs-1.2.0.dist-info/WHEEL
pyds_stubs-1.2.0.dist-info/METADATA
pyds_stubs-1.2.0.dist-info/RECORD
