Metadata-Version: 2.4
Name: pyds-stubs
Version: 1.2.0
Summary: Typing stubs for NVIDIA DeepStream Python Bindings
Keywords: nvidia,deepstream,bindings,stubs
Author: Niklas Kaaf
Author-email: Niklas Kaaf <nkaaf@protonmail.com>
License-File: LICENSE
Classifier: Development Status :: 5 - Production/Stable
Classifier: Intended Audience :: Developers
Classifier: License :: OSI Approved :: Apache Software License
Classifier: Programming Language :: Python
Classifier: Programming Language :: Python :: 3
Classifier: Programming Language :: Python :: 3 :: Only
Classifier: Programming Language :: Python :: 3.10
Classifier: Topic :: Documentation
Classifier: Typing :: Stubs Only
Requires-Dist: numpy
Requires-Dist: pygobject-stubs
Maintainer: Niklas Kaaf
Maintainer-email: Niklas Kaaf <nkaaf@protonmail.com>
Requires-Python: >=3.10, <3.11
Project-URL: Bug Tracker, https://github.com/nkaaf/pyds-stubs/issues
Project-URL: Releases, https://github.com/nkaaf/pyds-stubs/releases
Project-URL: Repository, https://github.com/nkaaf/pyds-stubs
